{
  "game_id": "2021038872",
  "metadata": {
    "date_jp": "2026年5月17日",
    "matchup": "読売ジャイアンツvs横浜DeNAベイスターズ"
  },
  "statline": {
    "player": "大勢",
    "era": "1.65",
    "innings": "1",
    "pitches": "16",
    "batters": "3",
    "hits": "0",
    "hr": "0",
    "k": "1",
    "bb": "0",
    "hbp": "0",
    "balk": "0",
    "runs": "0",
    "er": "0"
  },
  "pitches": [
    {
      "pa_index": "0810300",
      "pitcher": "大勢",
      "pitcher_id": "2103697",
      "pitcher_hand": "右",
      "batter": "筒香 嘉智",
      "batter_id": "1000002",
      "batter_hand": "左",
      "seq": "1",
      "pitchNo": "11",
      "pitchType": "ストレート",
      "speed": "154km/h",
      "result": "空振り",
      "top": 30.24,
      "left": 42.48
    },
    {
      "pa_index": "0810300",
      "pitcher": "大勢",
      "pitcher_id": "2103697",
      "pitcher_hand": "右",
      "batter": "筒香 嘉智",
      "batter_id": "1000002",
      "batter_hand": "左",
      "seq": "2",
      "pitchNo": "12",
      "pitchType": "ストレート",
      "speed": "155km/h",
      "result": "ボール",
      "top": 15.84,
      "left": 44.28
    },
    {
      "pa_index": "0810300",
      "pitcher": "大勢",
      "pitcher_id": "2103697",
      "pitcher_hand": "右",
      "batter": "筒香 嘉智",
      "batter_id": "1000002",
      "batter_hand": "左",
      "seq": "3",
      "pitchNo": "13",
      "pitchType": "フォーク",
      "speed": "139km/h",
      "result": "見逃し",
      "top": 39.96,
      "left": 24.84
    },
    {
      "pa_index": "0810300",
      "pitcher": "大勢",
      "pitcher_id": "2103697",
      "pitcher_hand": "右",
      "batter": "筒香 嘉智",
      "batter_id": "1000002",
      "batter_hand": "左",
      "seq": "4",
      "pitchNo": "14",
      "pitchType": "ストレート",
      "speed": "154km/h",
      "result": "ボール",
      "top": 35.64,
      "left": 46.08
    },
    {
      "pa_index": "0810300",
      "pitcher": "大勢",
      "pitcher_id": "2103697",
      "pitcher_hand": "右",
      "batter": "筒香 嘉智",
      "batter_id": "1000002",
      "batter_hand": "左",
      "seq": "5",
      "pitchNo": "15",
      "pitchType": "フォーク",
      "speed": "140km/h",
      "result": "ボール",
      "top": 57.599999999999994,
      "left": 26.279999999999998
    },
    {
      "pa_index": "0810300",
      "pitcher": "大勢",
      "pitcher_id": "2103697",
      "pitcher_hand": "右",
      "batter": "筒香 嘉智",
      "batter_id": "1000002",
      "batter_hand": "左",
      "seq": "6",
      "pitchNo": "16",
      "pitchType": "フォーク",
      "speed": "139km/h",
      "result": "空三振 [投手吼える]",
      "top": 25.919999999999998,
      "left": 20.88
    },
    {
      "pa_index": "0810200",
      "pitcher": "大勢",
      "pitcher_id": "2103697",
      "pitcher_hand": "右",
      "batter": "度会 隆輝",
      "batter_id": "1850873",
      "batter_hand": "左",
      "seq": "1",
      "pitchNo": "6",
      "pitchType": "フォーク",
      "speed": "139km/h",
      "result": "空振り",
      "top": 43.199999999999996,
      "left": 34.56
    },
    {
      "pa_index": "0810200",
      "pitcher": "大勢",
      "pitcher_id": "2103697",
      "pitcher_hand": "右",
      "batter": "度会 隆輝",
      "batter_id": "1850873",
      "batter_hand": "左",
      "seq": "2",
      "pitchNo": "7",
      "pitchType": "フォーク",
      "speed": "138km/h",
      "result": "ボール",
      "top": 35.28,
      "left": 43.199999999999996
    },
    {
      "pa_index": "0810200",
      "pitcher": "大勢",
      "pitcher_id": "2103697",
      "pitcher_hand": "右",
      "batter": "度会 隆輝",
      "batter_id": "1850873",
      "batter_hand": "左",
      "seq": "3",
      "pitchNo": "8",
      "pitchType": "フォーク",
      "speed": "142km/h",
      "result": "ファウル [自打球]",
      "top": 13.68,
      "left": 34.92
    },
    {
      "pa_index": "0810200",
      "pitcher": "大勢",
      "pitcher_id": "2103697",
      "pitcher_hand": "右",
      "batter": "度会 隆輝",
      "batter_id": "1850873",
      "batter_hand": "左",
      "seq": "4",
      "pitchNo": "9",
      "pitchType": "ストレート",
      "speed": "155km/h",
      "result": "ボール",
      "top": 20.88,
      "left": 43.559999999999995
    },
    {
      "pa_index": "0810200",
      "pitcher": "大勢",
      "pitcher_id": "2103697",
      "pitcher_hand": "右",
      "batter": "度会 隆輝",
      "batter_id": "1850873",
      "batter_hand": "左",
      "seq": "5",
      "pitchNo": "10",
      "pitchType": "ストレート",
      "speed": "152km/h",
      "result": "三ゴロ [バットの先]",
      "top": 32.76,
      "left": 41.4
    },
    {
      "pa_index": "0810100",
      "pitcher": "大勢",
      "pitcher_id": "2103697",
      "pitcher_hand": "右",
      "batter": "蝦名 達夫",
      "batter_id": "1900035",
      "batter_hand": "右",
      "seq": "1",
      "pitchNo": "1",
      "pitchType": "ストレート",
      "speed": "154km/h",
      "result": "見逃し",
      "top": 16.2,
      "left": 31.68
    },
    {
      "pa_index": "0810100",
      "pitcher": "大勢",
      "pitcher_id": "2103697",
      "pitcher_hand": "右",
      "batter": "蝦名 達夫",
      "batter_id": "1900035",
      "batter_hand": "右",
      "seq": "2",
      "pitchNo": "2",
      "pitchType": "ストレート",
      "speed": "155km/h",
      "result": "ファウル",
      "top": 15.84,
      "left": 43.199999999999996
    },
    {
      "pa_index": "0810100",
      "pitcher": "大勢",
      "pitcher_id": "2103697",
      "pitcher_hand": "右",
      "batter": "蝦名 達夫",
      "batter_id": "1900035",
      "batter_hand": "右",
      "seq": "3",
      "pitchNo": "3",
      "pitchType": "ストレート",
      "speed": "154km/h",
      "result": "ボール",
      "top": 34.56,
      "left": 5.3999999999999995
    },
    {
      "pa_index": "0810100",
      "pitcher": "大勢",
      "pitcher_id": "2103697",
      "pitcher_hand": "右",
      "batter": "蝦名 達夫",
      "batter_id": "1900035",
      "batter_hand": "右",
      "seq": "4",
      "pitchNo": "4",
      "pitchType": "フォーク",
      "speed": "139km/h",
      "result": "ファウル",
      "top": 49.68,
      "left": 12.24
    },
    {
      "pa_index": "0810100",
      "pitcher": "大勢",
      "pitcher_id": "2103697",
      "pitcher_hand": "右",
      "batter": "蝦名 達夫",
      "batter_id": "1900035",
      "batter_hand": "右",
      "seq": "5",
      "pitchNo": "5",
      "pitchType": "フォーク",
      "speed": "138km/h",
      "result": "捕邪飛",
      "top": 29.16,
      "left": 42.48
    }
  ]
}