{
  "game_id": "2021038791",
  "metadata": {
    "date_jp": "2026年4月30日",
    "matchup": "埼玉西武ライオンズvs北海道日本ハムファイターズ"
  },
  "statline": {
    "player": "甲斐野 央",
    "era": "3.60",
    "innings": "0.2",
    "pitches": "7",
    "batters": "2",
    "hits": "0",
    "hr": "0",
    "k": "1",
    "bb": "0",
    "hbp": "0",
    "balk": "0",
    "runs": "0",
    "er": "0"
  },
  "pitches": [
    {
      "pa_index": "0810700",
      "pitcher": "甲斐野 央",
      "pitcher_id": "1800106",
      "pitcher_hand": "右",
      "batter": "レイエス",
      "batter_id": "1860140",
      "batter_hand": "右",
      "seq": "1",
      "pitchNo": "4",
      "pitchType": "スライダー",
      "speed": "141km/h",
      "result": "ボール",
      "top": 25.2,
      "left": 2.88
    },
    {
      "pa_index": "0810700",
      "pitcher": "甲斐野 央",
      "pitcher_id": "1800106",
      "pitcher_hand": "右",
      "batter": "レイエス",
      "batter_id": "1860140",
      "batter_hand": "右",
      "seq": "2",
      "pitchNo": "5",
      "pitchType": "スライダー",
      "speed": "141km/h",
      "result": "ファウル",
      "top": 52.559999999999995,
      "left": 17.28
    },
    {
      "pa_index": "0810700",
      "pitcher": "甲斐野 央",
      "pitcher_id": "1800106",
      "pitcher_hand": "右",
      "batter": "レイエス",
      "batter_id": "1860140",
      "batter_hand": "右",
      "seq": "3",
      "pitchNo": "6",
      "pitchType": "フォーク",
      "speed": "139km/h",
      "result": "空振り",
      "top": 18.36,
      "left": 9.719999999999999
    },
    {
      "pa_index": "0810700",
      "pitcher": "甲斐野 央",
      "pitcher_id": "1800106",
      "pitcher_hand": "右",
      "batter": "レイエス",
      "batter_id": "1860140",
      "batter_hand": "右",
      "seq": "4",
      "pitchNo": "7",
      "pitchType": "フォーク",
      "speed": "142km/h",
      "result": "空三振 [ワンバウンド]",
      "top": 62.64,
      "left": 26.279999999999998
    },
    {
      "pa_index": "0810600",
      "pitcher": "甲斐野 央",
      "pitcher_id": "1800106",
      "pitcher_hand": "右",
      "batter": "郡司 裕也",
      "batter_id": "1900040",
      "batter_hand": "右",
      "seq": "1",
      "pitchNo": "1",
      "pitchType": "ストレート",
      "speed": "156km/h",
      "result": "見逃し",
      "top": 38.16,
      "left": 26.64
    },
    {
      "pa_index": "0810600",
      "pitcher": "甲斐野 央",
      "pitcher_id": "1800106",
      "pitcher_hand": "右",
      "batter": "郡司 裕也",
      "batter_id": "1900040",
      "batter_hand": "右",
      "seq": "2",
      "pitchNo": "2",
      "pitchType": "ストレート",
      "speed": "157km/h",
      "result": "空振り",
      "top": 30.959999999999997,
      "left": 20.52
    },
    {
      "pa_index": "0810600",
      "pitcher": "甲斐野 央",
      "pitcher_id": "1800106",
      "pitcher_hand": "右",
      "batter": "郡司 裕也",
      "batter_id": "1900040",
      "batter_hand": "右",
      "seq": "3",
      "pitchNo": "3",
      "pitchType": "フォーク",
      "speed": "143km/h",
      "result": "中犠飛 [泳ぎ]",
      "top": 55.08,
      "left": 16.2
    }
  ]
}